{
	"credit": "Made with Blockbench",
	"texture_size": [32, 32],
	"textures": {
		"2": "block/flower/red_tulip",
		"particle": "block/flower/red_tulip"
	},
	"elements": [
		{
			"name": "flover",
			"from": [6.6, 6.3, 6.45],
			"to": [9.6, 11.3, 9.45],
			"rotation": {"angle": 0, "axis": "x", "origin": [8.1, 8.75, 7.95]},
			"faces": {
				"north": {"uv": [13, 3, 16, 8], "texture": "#2"},
				"east": {"uv": [13, 3, 16, 8], "texture": "#2"},
				"south": {"uv": [13, 3, 16, 8], "texture": "#2"},
				"west": {"uv": [13, 3, 16, 8], "texture": "#2"},
				"up": {"uv": [13, 0, 16, 3], "texture": "#2"},
				"down": {"uv": [10, 0, 13, 3], "texture": "#2"}
			}
		},
		{
			"name": "flover_leves5",
			"from": [5.17836, 0.03362, 5.49027],
			"to": [13.17836, 8.03362, 5.49027],
			"rotation": {"angle": -45, "axis": "y", "origin": [5.67836, 3.13362, 5.49027]},
			"faces": {
				"north": {"uv": [0, 0, 7.75, 8], "texture": "#2"},
				"south": {"uv": [0, 0, 7.75, 8], "texture": "#2"}
			}
		},
		{
			"name": "flover_leves5",
			"from": [10.67836, 0.03362, 4.99027],
			"to": [10.67836, 8.03362, 12.99027],
			"rotation": {"angle": -45, "axis": "y", "origin": [10.67836, 3.13362, 5.49027]},
			"faces": {
				"east": {"uv": [0, 0, 7.75, 8], "texture": "#2"},
				"west": {"uv": [0, 0, 7.75, 8], "texture": "#2"}
			}
		},
		{
			"name": "flover_leves5",
			"from": [7.67836, 0.03362, 7.99027],
			"to": [8.67836, 6.23362, 7.99027],
			"rotation": {"angle": 0, "axis": "x", "origin": [10.67836, 0.18771, 7.05]},
			"faces": {
				"north": {"uv": [3.5, 2, 4.5, 7.5], "texture": "#2"},
				"south": {"uv": [3.5, 2, 4.5, 7.5], "texture": "#2"}
			}
		},
		{
			"name": "flover_leves6",
			"from": [8.17836, 0.03362, 8.49027],
			"to": [8.17836, 6.33362, 7.49027],
			"rotation": {"angle": 0, "axis": "y", "origin": [8.17836, 5.03362, 7.99027]},
			"faces": {
				"east": {"uv": [3.5, 1.9, 4.5, 7.25], "texture": "#2"},
				"west": {"uv": [3.5, 2, 4.5, 7.25], "texture": "#2"}
			}
		},
		{
			"name": "flover_leves6",
			"from": [9.6, 6.3, 5.8614],
			"to": [6.6, 9.3, 5.8614],
			"rotation": {"angle": -22.5, "axis": "x", "origin": [8.1, 7.78379, 5.8614]},
			"faces": {
				"north": {"uv": [10, 5, 13, 8], "texture": "#2"},
				"south": {"uv": [10, 5, 13, 8], "texture": "#2"}
			}
		},
		{
			"name": "flover_leves6",
			"from": [10.04291, 6.3, 9.5],
			"to": [10.04291, 9.3, 6.5],
			"rotation": {"angle": -22.5, "axis": "z", "origin": [10.04291, 7.51299, 8]},
			"faces": {
				"east": {"uv": [10, 5, 13, 8], "texture": "#2"},
				"west": {"uv": [10, 5, 13, 8], "texture": "#2"}
			}
		},
		{
			"name": "flover_leves6",
			"from": [5.90464, 6.3, 9.5],
			"to": [5.90464, 9.3, 6.5],
			"rotation": {"angle": 22.5, "axis": "z", "origin": [5.90464, 8.0794, 8]},
			"faces": {
				"east": {"uv": [10, 5, 13, 8], "texture": "#2"},
				"west": {"uv": [10, 5, 13, 8], "texture": "#2"}
			}
		},
		{
			"name": "flover_leves6",
			"from": [9.6, 6.29987, 10.10316],
			"to": [6.6, 9.29987, 10.10316],
			"rotation": {"angle": 22.5, "axis": "x", "origin": [8.1, 7.79987, 10.10316]},
			"faces": {
				"north": {"uv": [10, 5, 13, 8], "texture": "#2"},
				"south": {"uv": [10, 5, 13, 8], "texture": "#2"}
			}
		}
	],
	"display": {
		"thirdperson_righthand": {
			"rotation": [-28, 0, 0],
			"translation": [0, 7, -3.75]
		},
		"thirdperson_lefthand": {
			"rotation": [-28, 0, 0],
			"translation": [0, 7, -3.75]
		},
		"firstperson_righthand": {
			"rotation": [4, 18, 15],
			"translation": [-4, 6.25, 6.25],
			"scale": [0.5, 0.5, 0.5]
		},
		"firstperson_lefthand": {
			"rotation": [4, 18, 15],
			"translation": [-4, 6.25, 6.25],
			"scale": [0.5, 0.5, 0.5]
		},
		"ground": {
			"rotation": [0, 0, 93],
			"translation": [-4.5, 0.75, 1]
		},
		"gui": {
			"rotation": [0, 60, 40],
			"translation": [-1.5, 2, 0]
		},
		"head": {
			"translation": [0, 14.75, 0]
		},
		"fixed": {
			"translation": [0, 2, 0]
		}
	},
	"groups": [
		{
			"name": "group",
			"origin": [8, 8, 8],
			"color": 0,
			"children": [
				0,
				{
					"name": "flover_leves6",
					"origin": [7.87836, 4.53362, 7.99027],
					"color": 0,
					"children": [
						1,
						2,
						3,
						4,
						{
							"name": "flover_leves6",
							"origin": [7.67836, 11.03362, 2.99027],
							"color": 0,
							"children": [5, 6, 7, 8]
						}
					]
				}
			]
		}
	]
}